{
  "directed": true,
  "graph": [],
  "nodes": [
    {"id":"Administration of justice","URI":"http://www.parliament.uk/topics/Administration-of-justice.htm"},
{"id":"Adult education","URI":"http://www.parliament.uk/topics/Adult-education.htm"},
{"id":"Afghanistan","URI":"http://www.parliament.uk/topics/Afghanistan.htm"},
{"id":"Africa","URI":"http://www.parliament.uk/topics/Africa.htm"},
{"id":"Age discrimination","URI":"http://www.parliament.uk/topics/Age-discrimination.htm"},
{"id":"Agriculture","URI":"http://www.parliament.uk/topics/Agriculture.htm"},
{"id":"Agriculture and environment","URI":"http://www.parliament.uk/topics/Agriculture-and-environment.htm"},
{"id":"Agriculture, animals, food and rural affairs","URI":"http://www.parliament.uk/topics/Agriculture-animals-food-and-rural-affairs.htm"},
{"id":"Alcoholism","URI":"http://www.parliament.uk/topics/Alcoholism.htm"},
{"id":"Alternatives to prison","URI":"http://www.parliament.uk/topics/Alternatives-to-prison.htm"},
{"id":"Ambulance services","URI":"http://www.parliament.uk/topics/Ambulance-services.htm"},
{"id":"Animal diseases","URI":"http://www.parliament.uk/topics/Animal-diseases.htm"},
{"id":"Animal experiments","URI":"http://www.parliament.uk/topics/Animal-experiments.htm"},
{"id":"Animal welfare","URI":"http://www.parliament.uk/topics/Animal-welfare.htm"},
{"id":"Animals","URI":"http://www.parliament.uk/topics/Animals.htm"},
{"id":"Anti-social behaviour","URI":"http://www.parliament.uk/topics/Anti-social-behaviour.htm"},
{"id":"Armed forces","URI":"http://www.parliament.uk/topics/Armed-forces.htm"},
{"id":"Armed forces welfare","URI":"http://www.parliament.uk/topics/Armed-forces-welfare.htm"},
{"id":"Arms control","URI":"http://www.parliament.uk/topics/Arms-control.htm"},
{"id":"Art works","URI":"http://www.parliament.uk/topics/Art-works.htm"},
{"id":"Arts","URI":"http://www.parliament.uk/topics/Arts.htm"},
{"id":"Asia","URI":"http://www.parliament.uk/topics/Asia.htm"},
{"id":"Asylum","URI":"http://www.parliament.uk/topics/Asylum.htm"},
{"id":"Asylum, immigration and nationality","URI":"http://www.parliament.uk/topics/Asylum-immigration-and-nationality.htm"},
{"id":"Australasia","URI":"http://www.parliament.uk/topics/Australasia.htm"},
{"id":"Aviation","URI":"http://www.parliament.uk/topics/Aviation.htm"},
{"id":"Ballistic missile defence","URI":"http://www.parliament.uk/topics/Ballistic-missile-defence.htm"},
{"id":"Benefits administration","URI":"http://www.parliament.uk/topics/Benefits-administration.htm"},
{"id":"Benefits policy","URI":"http://www.parliament.uk/topics/Benefits-policy.htm"},
{"id":"Bereavement benefits","URI":"http://www.parliament.uk/topics/Bereavement-benefits.htm"},
{"id":"Biodiversity","URI":"http://www.parliament.uk/topics/Biodiversity.htm"},
{"id":"Broadcasting","URI":"http://www.parliament.uk/topics/Broadcasting.htm"},
{"id":"Burial and cremation","URI":"http://www.parliament.uk/topics/Burial-and-cremation.htm"},
{"id":"Buses","URI":"http://www.parliament.uk/topics/Buses.htm"},
{"id":"Business support","URI":"http://www.parliament.uk/topics/Business-support.htm"},
{"id":"Business, industry and consumers","URI":"http://www.parliament.uk/topics/Business-industry-and-consumers.htm"},
{"id":"By-elections","URI":"http://www.parliament.uk/topics/By-elections.htm"},
{"id":"Census","URI":"http://www.parliament.uk/topics/Census.htm"},
{"id":"Central government","URI":"http://www.parliament.uk/topics/Central-government.htm"},
{"id":"Charities","URI":"http://www.parliament.uk/topics/Charities.htm"},
{"id":"Child care","URI":"http://www.parliament.uk/topics/Child-care.htm"},
{"id":"Child support","URI":"http://www.parliament.uk/topics/Child-support.htm"},
{"id":"Children and families","URI":"http://www.parliament.uk/topics/Children-and-families.htm"},
{"id":"Childrens social services","URI":"http://www.parliament.uk/topics/Childrens-social-services.htm"},
{"id":"Church and state","URI":"http://www.parliament.uk/topics/Church-and-state.htm"},
{"id":"Civil law","URI":"http://www.parliament.uk/topics/Civil-law.htm"},
{"id":"Civil partnerships","URI":"http://www.parliament.uk/topics/Civil-partnerships.htm"},
{"id":"Civil Service","URI":"http://www.parliament.uk/topics/Civil-Service.htm"},
{"id":"Climate change","URI":"http://www.parliament.uk/topics/Climate-change.htm"},
{"id":"Coal","URI":"http://www.parliament.uk/topics/Coal.htm"},
{"id":"Cohabitation","URI":"http://www.parliament.uk/topics/Cohabitation.htm"},
{"id":"Common Agricultural Policy","URI":"http://www.parliament.uk/topics/Common-Agricultural-Policy.htm"},
{"id":"Communicable diseases","URI":"http://www.parliament.uk/topics/Communicable-diseases.htm"},
{"id":"Communities and families","URI":"http://www.parliament.uk/topics/Communities-and-families.htm"},
{"id":"Community care","URI":"http://www.parliament.uk/topics/Community-care.htm"},
{"id":"Companies","URI":"http://www.parliament.uk/topics/Companies.htm"},
{"id":"Competition","URI":"http://www.parliament.uk/topics/Competition.htm"},
{"id":"Constitution","URI":"http://www.parliament.uk/topics/Constitution.htm"},
{"id":"Construction industry","URI":"http://www.parliament.uk/topics/Construction-industry.htm"},
{"id":"Consumers","URI":"http://www.parliament.uk/topics/Consumers.htm"},
{"id":"Coroners","URI":"http://www.parliament.uk/topics/Coroners.htm"},
{"id":"Countryside","URI":"http://www.parliament.uk/topics/Countryside.htm"},
{"id":"Courts","URI":"http://www.parliament.uk/topics/Courts.htm"},
{"id":"Crime","URI":"http://www.parliament.uk/topics/Crime.htm"},
{"id":"Crime, civil law, justice and rights","URI":"http://www.parliament.uk/topics/Crime-civil-law-justice-and-rights.htm"},
{"id":"Crimes of violence","URI":"http://www.parliament.uk/topics/Crimes-of-violence.htm"},
{"id":"Criminal law","URI":"http://www.parliament.uk/topics/Criminal-law.htm"},
{"id":"Crown","URI":"http://www.parliament.uk/topics/Crown.htm"},
{"id":"Cultural heritage","URI":"http://www.parliament.uk/topics/Cultural-heritage.htm"},
{"id":"Culture, media and sport","URI":"http://www.parliament.uk/topics/Culture-media-and-sport.htm"},
{"id":"Cycling","URI":"http://www.parliament.uk/topics/Cycling.htm"},
{"id":"Data protection","URI":"http://www.parliament.uk/topics/Data-protection.htm"},
{"id":"Death","URI":"http://www.parliament.uk/topics/Death.htm"},
{"id":"Defence","URI":"http://www.parliament.uk/topics/Defence.htm"},
{"id":"Defence equipment and procurement","URI":"http://www.parliament.uk/topics/Defence-equipment-and-procurement.htm"},
{"id":"Defence expenditure","URI":"http://www.parliament.uk/topics/Defence-expenditure.htm"},
{"id":"Defence policy","URI":"http://www.parliament.uk/topics/Defence-policy.htm"},
{"id":"Devolution","URI":"http://www.parliament.uk/topics/Devolution.htm"},
{"id":"Disability discrimination","URI":"http://www.parliament.uk/topics/Disability-discrimination.htm"},
{"id":"Diseases","URI":"http://www.parliament.uk/topics/Diseases.htm"},
{"id":"Divorce","URI":"http://www.parliament.uk/topics/Divorce.htm"},
{"id":"Drugs crimes","URI":"http://www.parliament.uk/topics/Drugs-crimes.htm"},
{"id":"Drugs misuse","URI":"http://www.parliament.uk/topics/Drugs-misuse.htm"},
{"id":"Eastern Europe","URI":"http://www.parliament.uk/topics/Eastern-Europe.htm"},
{"id":"Economic and monetary union","URI":"http://www.parliament.uk/topics/Economic-and-monetary-union.htm"},
{"id":"Economic policy","URI":"http://www.parliament.uk/topics/Economic-policy.htm"},
{"id":"Economic situation","URI":"http://www.parliament.uk/topics/Economic-situation.htm"},
{"id":"Economy and finance","URI":"http://www.parliament.uk/topics/Economy-and-finance.htm"},
{"id":"Education","URI":"http://www.parliament.uk/topics/Education.htm"},
{"id":"Election expenditure","URI":"http://www.parliament.uk/topics/Election-expenditure.htm"},
{"id":"Election results : international","URI":"http://www.parliament.uk/topics/Election-results-:-international.htm"},
{"id":"Election results : UK","URI":"http://www.parliament.uk/topics/Election-results-:-UK.htm"},
{"id":"Elections","URI":"http://www.parliament.uk/topics/Elections.htm"},
{"id":"Electoral franchise","URI":"http://www.parliament.uk/topics/Electoral-franchise.htm"},
{"id":"Electoral register","URI":"http://www.parliament.uk/topics/Electoral-register.htm"},
{"id":"Electoral systems","URI":"http://www.parliament.uk/topics/Electoral-systems.htm"},
{"id":"Electricity","URI":"http://www.parliament.uk/topics/Electricity.htm"},
{"id":"Emergencies and disaster management","URI":"http://www.parliament.uk/topics/Emergencies-and-disaster-management.htm"},
{"id":"Emergency services","URI":"http://www.parliament.uk/topics/Emergency-services.htm"},
{"id":"Employment","URI":"http://www.parliament.uk/topics/Employment.htm"},
{"id":"Employment and training","URI":"http://www.parliament.uk/topics/Employment-and-training.htm"},
{"id":"Employment schemes","URI":"http://www.parliament.uk/topics/Employment-schemes.htm"},
{"id":"Empty property","URI":"http://www.parliament.uk/topics/Empty-property.htm"},
{"id":"Energy","URI":"http://www.parliament.uk/topics/Energy.htm"},
{"id":"Energy and environment","URI":"http://www.parliament.uk/topics/Energy-and-environment.htm"},
{"id":"Energy conservation","URI":"http://www.parliament.uk/topics/Energy-conservation.htm"},
{"id":"Environmental protection","URI":"http://www.parliament.uk/topics/Environmental-protection.htm"},
{"id":"Equality","URI":"http://www.parliament.uk/topics/Equality.htm"},
{"id":"Ethnic groups","URI":"http://www.parliament.uk/topics/Ethnic-groups.htm"},
{"id":"EU budget","URI":"http://www.parliament.uk/topics/EU-budget.htm"},
{"id":"EU Council of Ministers","URI":"http://www.parliament.uk/topics/EU-Council-of-Ministers.htm"},
{"id":"EU defence policy","URI":"http://www.parliament.uk/topics/EU-defence-policy.htm"},
{"id":"EU enlargement","URI":"http://www.parliament.uk/topics/EU-enlargement.htm"},
{"id":"EU external relations","URI":"http://www.parliament.uk/topics/EU-external-relations.htm"},
{"id":"EU grants and loans","URI":"http://www.parliament.uk/topics/EU-grants-and-loans.htm"},
{"id":"EU institutions","URI":"http://www.parliament.uk/topics/EU-institutions.htm"},
{"id":"EU law and treaties","URI":"http://www.parliament.uk/topics/EU-law-and-treaties.htm"},
{"id":"EU political integration","URI":"http://www.parliament.uk/topics/EU-political-integration.htm"},
{"id":"Europe","URI":"http://www.parliament.uk/topics/Europe.htm"},
{"id":"European Commission","URI":"http://www.parliament.uk/topics/European-Commission.htm"},
{"id":"European Council","URI":"http://www.parliament.uk/topics/European-Council.htm"},
{"id":"European Parliament","URI":"http://www.parliament.uk/topics/European-Parliament.htm"},
{"id":"European Union","URI":"http://www.parliament.uk/topics/European-Union.htm"},
{"id":"Falkland Islands","URI":"http://www.parliament.uk/topics/Falkland-Islands.htm"},
{"id":"Family benefits","URI":"http://www.parliament.uk/topics/Family-benefits.htm"},
{"id":"Family law","URI":"http://www.parliament.uk/topics/Family-law.htm"},
{"id":"Farmers","URI":"http://www.parliament.uk/topics/Farmers.htm"},
{"id":"Financial institutions","URI":"http://www.parliament.uk/topics/Financial-institutions.htm"},
{"id":"Financial services","URI":"http://www.parliament.uk/topics/Financial-services.htm"},
{"id":"Fire services","URI":"http://www.parliament.uk/topics/Fire-services.htm"},
{"id":"Firearms","URI":"http://www.parliament.uk/topics/Firearms.htm"},
{"id":"Fisheries","URI":"http://www.parliament.uk/topics/Fisheries.htm"},
{"id":"Flooding","URI":"http://www.parliament.uk/topics/Flooding.htm"},
{"id":"Food","URI":"http://www.parliament.uk/topics/Food.htm"},
{"id":"Foreign and Commonwealth Office","URI":"http://www.parliament.uk/topics/Foreign-and-Commonwealth-Office.htm"},
{"id":"Forestry","URI":"http://www.parliament.uk/topics/Forestry.htm"},
{"id":"Freedom of information","URI":"http://www.parliament.uk/topics/Freedom-of-information.htm"},
{"id":"Fuel poverty","URI":"http://www.parliament.uk/topics/Fuel-poverty.htm"},
{"id":"Funerals","URI":"http://www.parliament.uk/topics/Funerals.htm"},
{"id":"Further education","URI":"http://www.parliament.uk/topics/Further-education.htm"},
{"id":"Gambling","URI":"http://www.parliament.uk/topics/Gambling.htm"},
{"id":"Gender recognition","URI":"http://www.parliament.uk/topics/Gender-recognition.htm"},
{"id":"General elections","URI":"http://www.parliament.uk/topics/General-elections.htm"},
{"id":"Genetics","URI":"http://www.parliament.uk/topics/Genetics.htm"},
{"id":"Health education and preventive medicine","URI":"http://www.parliament.uk/topics/Health-education-and-preventive-medicine.htm"},
{"id":"Health finance","URI":"http://www.parliament.uk/topics/Health-finance.htm"},
{"id":"Health services","URI":"http://www.parliament.uk/topics/Health-services.htm"},
{"id":"Health services and medicine","URI":"http://www.parliament.uk/topics/Health-services-and-medicine.htm"},
{"id":"Health staff and professions","URI":"http://www.parliament.uk/topics/Health-staff-and-professions.htm"},
{"id":"Hedges and ditches","URI":"http://www.parliament.uk/topics/Hedges-and-ditches.htm"},
{"id":"Higher education","URI":"http://www.parliament.uk/topics/Higher-education.htm"},
{"id":"Homelessness","URI":"http://www.parliament.uk/topics/Homelessness.htm"},
{"id":"House of Commons","URI":"http://www.parliament.uk/topics/House-of-Commons.htm"},
{"id":"House of Lords","URI":"http://www.parliament.uk/topics/House-of-Lords.htm"},
{"id":"Housing","URI":"http://www.parliament.uk/topics/Housing.htm"},
{"id":"Housing adaptations","URI":"http://www.parliament.uk/topics/Housing-adaptations.htm"},
{"id":"Housing and planning","URI":"http://www.parliament.uk/topics/Housing-and-planning.htm"},
{"id":"Housing benefits","URI":"http://www.parliament.uk/topics/Housing-benefits.htm"},
{"id":"Housing standards","URI":"http://www.parliament.uk/topics/Housing-standards.htm"},
{"id":"Housing supply","URI":"http://www.parliament.uk/topics/Housing-supply.htm"},
{"id":"Human rights","URI":"http://www.parliament.uk/topics/Human-rights.htm"},
{"id":"Immigration","URI":"http://www.parliament.uk/topics/Immigration.htm"},
{"id":"Incomes and poverty","URI":"http://www.parliament.uk/topics/Incomes-and-poverty.htm"},
{"id":"Industrial health and safety","URI":"http://www.parliament.uk/topics/Industrial-health-and-safety.htm"},
{"id":"Industrial relations","URI":"http://www.parliament.uk/topics/Industrial-relations.htm"},
{"id":"Industry","URI":"http://www.parliament.uk/topics/Industry.htm"},
{"id":"Information technology","URI":"http://www.parliament.uk/topics/Information-technology.htm"},
{"id":"Insolvency","URI":"http://www.parliament.uk/topics/Insolvency.htm"},
{"id":"Intellectual property","URI":"http://www.parliament.uk/topics/Intellectual-property.htm"},
{"id":"Intelligence services","URI":"http://www.parliament.uk/topics/Intelligence-services.htm"},
{"id":"International affairs","URI":"http://www.parliament.uk/topics/International-affairs.htm"},
{"id":"International development","URI":"http://www.parliament.uk/topics/International-development.htm"},
{"id":"International economic relations","URI":"http://www.parliament.uk/topics/International-economic-relations.htm"},
{"id":"International law","URI":"http://www.parliament.uk/topics/International-law.htm"},
{"id":"International organisations","URI":"http://www.parliament.uk/topics/International-organisations.htm"},
{"id":"International politics and government","URI":"http://www.parliament.uk/topics/International-politics-and-government.htm"},
{"id":"International trade","URI":"http://www.parliament.uk/topics/International-trade.htm"},
{"id":"Internet and cybercrime","URI":"http://www.parliament.uk/topics/Internet-and-cybercrime.htm"},
{"id":"Iran","URI":"http://www.parliament.uk/topics/Iran.htm"},
{"id":"Iraq","URI":"http://www.parliament.uk/topics/Iraq.htm"},
{"id":"Land law","URI":"http://www.parliament.uk/topics/Land-law.htm"},
{"id":"Latin America","URI":"http://www.parliament.uk/topics/Latin-America.htm"},
{"id":"Legal aid","URI":"http://www.parliament.uk/topics/Legal-aid.htm"},
{"id":"Legal profession","URI":"http://www.parliament.uk/topics/Legal-profession.htm"},
{"id":"Legislative process","URI":"http://www.parliament.uk/topics/Legislative-process.htm"},
{"id":"Leisure","URI":"http://www.parliament.uk/topics/Leisure.htm"},
{"id":"Libraries","URI":"http://www.parliament.uk/topics/Libraries.htm"},
{"id":"Licensing","URI":"http://www.parliament.uk/topics/Licensing.htm"},
{"id":"Limitation of actions","URI":"http://www.parliament.uk/topics/Limitation-of-actions.htm"},
{"id":"Loans","URI":"http://www.parliament.uk/topics/Loans.htm"},
{"id":"Local authorities: education","URI":"http://www.parliament.uk/topics/Local-authorities:-education.htm"},
{"id":"Local government","URI":"http://www.parliament.uk/topics/Local-government.htm"},
{"id":"Lord Speaker","URI":"http://www.parliament.uk/topics/Lord-Speaker.htm"},
{"id":"Manufacturing industries","URI":"http://www.parliament.uk/topics/Manufacturing-industries.htm"},
{"id":"Marine environment","URI":"http://www.parliament.uk/topics/Marine-environment.htm"},
{"id":"Marriage","URI":"http://www.parliament.uk/topics/Marriage.htm"},
{"id":"Media","URI":"http://www.parliament.uk/topics/Media.htm"},
{"id":"Medical ethics","URI":"http://www.parliament.uk/topics/Medical-ethics.htm"},
{"id":"Medicine","URI":"http://www.parliament.uk/topics/Medicine.htm"},
{"id":"Members of Parliament","URI":"http://www.parliament.uk/topics/Members-of-Parliament.htm"},
{"id":"Members of the Lords","URI":"http://www.parliament.uk/topics/Members-of-the-Lords.htm"},
{"id":"Mental health","URI":"http://www.parliament.uk/topics/Mental-health.htm"},
{"id":"Middle East","URI":"http://www.parliament.uk/topics/Middle-East.htm"},
{"id":"Military operations","URI":"http://www.parliament.uk/topics/Military-operations.htm"},
{"id":"Ministers","URI":"http://www.parliament.uk/topics/Ministers.htm"},
{"id":"Mortgages","URI":"http://www.parliament.uk/topics/Mortgages.htm"},
{"id":"Motorcycles","URI":"http://www.parliament.uk/topics/Motorcycles.htm"},
{"id":"Museums and galleries","URI":"http://www.parliament.uk/topics/Museums-and-galleries.htm"},
{"id":"National Assembly for Wales","URI":"http://www.parliament.uk/topics/National-Assembly-for-Wales.htm"},
{"id":"National insurance","URI":"http://www.parliament.uk/topics/National-insurance.htm"},
{"id":"National Lottery","URI":"http://www.parliament.uk/topics/National-Lottery.htm"},
{"id":"Nationality","URI":"http://www.parliament.uk/topics/Nationality.htm"},
{"id":"NATO","URI":"http://www.parliament.uk/topics/NATO.htm"},
{"id":"Nature conservation","URI":"http://www.parliament.uk/topics/Nature-conservation.htm"},
{"id":"Non-departmental public bodies","URI":"http://www.parliament.uk/topics/Non-departmental-public-bodies.htm"},
{"id":"North America","URI":"http://www.parliament.uk/topics/North-America.htm"},
{"id":"Northern Ireland Assembly","URI":"http://www.parliament.uk/topics/Northern-Ireland-Assembly.htm"},
{"id":"Nuclear power","URI":"http://www.parliament.uk/topics/Nuclear-power.htm"},
{"id":"Obesity","URI":"http://www.parliament.uk/topics/Obesity.htm"},
{"id":"Offensive weapons","URI":"http://www.parliament.uk/topics/Offensive-weapons.htm"},
{"id":"Ofsted","URI":"http://www.parliament.uk/topics/Ofsted.htm"},
{"id":"Oil, petrol and natural gas","URI":"http://www.parliament.uk/topics/Oil-petrol-and-natural-gas.htm"},
{"id":"Older people","URI":"http://www.parliament.uk/topics/Older-people.htm"},
{"id":"Organic farming","URI":"http://www.parliament.uk/topics/Organic-farming.htm"},
{"id":"Organisation for Security and Cooperation in Europe","URI":"http://www.parliament.uk/topics/Organisation-for-Security-and-Cooperation-in-Europe.htm"},
{"id":"Overcrowding","URI":"http://www.parliament.uk/topics/Overcrowding.htm"},
{"id":"Overseas territories","URI":"http://www.parliament.uk/topics/Overseas-territories.htm"},
{"id":"Owner occupation","URI":"http://www.parliament.uk/topics/Owner-occupation.htm"},
{"id":"Parliament","URI":"http://www.parliament.uk/topics/Parliament.htm"},
{"id":"Parliament, government and politics","URI":"http://www.parliament.uk/topics/Parliament-government-and-politics.htm"},
{"id":"Parliamentary procedure","URI":"http://www.parliament.uk/topics/Parliamentary-procedure.htm"},
{"id":"Patient rights and complaints","URI":"http://www.parliament.uk/topics/Patient-rights-and-complaints.htm"},
{"id":"Pay","URI":"http://www.parliament.uk/topics/Pay.htm"},
{"id":"Pensions","URI":"http://www.parliament.uk/topics/Pensions.htm"},
{"id":"Performing arts","URI":"http://www.parliament.uk/topics/Performing-arts.htm"},
{"id":"Personal injury","URI":"http://www.parliament.uk/topics/Personal-injury.htm"},
{"id":"Planning","URI":"http://www.parliament.uk/topics/Planning.htm"},
{"id":"Police","URI":"http://www.parliament.uk/topics/Police.htm"},
{"id":"Political parties","URI":"http://www.parliament.uk/topics/Political-parties.htm"},
{"id":"Pollution","URI":"http://www.parliament.uk/topics/Pollution.htm"},
{"id":"Population","URI":"http://www.parliament.uk/topics/Population.htm"},
{"id":"Postal services","URI":"http://www.parliament.uk/topics/Postal-services.htm"},
{"id":"Powers of attorney","URI":"http://www.parliament.uk/topics/Powers-of-attorney.htm"},
{"id":"Pre-school education","URI":"http://www.parliament.uk/topics/Pre-school-education.htm"},
{"id":"Press","URI":"http://www.parliament.uk/topics/Press.htm"},
{"id":"Prisons","URI":"http://www.parliament.uk/topics/Prisons.htm"},
{"id":"Privacy","URI":"http://www.parliament.uk/topics/Privacy.htm"},
{"id":"Private rented housing","URI":"http://www.parliament.uk/topics/Private-rented-housing.htm"},
{"id":"Public administration","URI":"http://www.parliament.uk/topics/Public-administration.htm"},
{"id":"Public expenditure","URI":"http://www.parliament.uk/topics/Public-expenditure.htm"},
{"id":"Public inquiries","URI":"http://www.parliament.uk/topics/Public-inquiries.htm"},
{"id":"Public order offences","URI":"http://www.parliament.uk/topics/Public-order-offences.htm"},
{"id":"Racial discrimination","URI":"http://www.parliament.uk/topics/Racial-discrimination.htm"},
{"id":"Railways","URI":"http://www.parliament.uk/topics/Railways.htm"},
{"id":"Regeneration","URI":"http://www.parliament.uk/topics/Regeneration.htm"},
{"id":"Regional assemblies","URI":"http://www.parliament.uk/topics/Regional-assemblies.htm"},
{"id":"Regional development agencies","URI":"http://www.parliament.uk/topics/Regional-development-agencies.htm"},
{"id":"Regional planning and development","URI":"http://www.parliament.uk/topics/Regional-planning-and-development.htm"},
{"id":"Registration of births, deaths and marriages","URI":"http://www.parliament.uk/topics/Registration-of-births-deaths-and-marriages.htm"},
{"id":"Regulation","URI":"http://www.parliament.uk/topics/Regulation.htm"},
{"id":"Religion and faith communities","URI":"http://www.parliament.uk/topics/Religion-and-faith-communities.htm"},
{"id":"Religious discrimination","URI":"http://www.parliament.uk/topics/Religious-discrimination.htm"},
{"id":"Renewable energy","URI":"http://www.parliament.uk/topics/Renewable-energy.htm"},
{"id":"Research and innovation","URI":"http://www.parliament.uk/topics/Research-and-innovation.htm"},
{"id":"Roads","URI":"http://www.parliament.uk/topics/Roads.htm"},
{"id":"Russia","URI":"http://www.parliament.uk/topics/Russia.htm"},
{"id":"Schools","URI":"http://www.parliament.uk/topics/Schools.htm"},
{"id":"Science","URI":"http://www.parliament.uk/topics/Science.htm"},
{"id":"Science and technology","URI":"http://www.parliament.uk/topics/Science-and-technology.htm"},
{"id":"Scottish Parliament","URI":"http://www.parliament.uk/topics/Scottish-Parliament.htm"},
{"id":"Security industry","URI":"http://www.parliament.uk/topics/Security-industry.htm"},
{"id":"Service industries","URI":"http://www.parliament.uk/topics/Service-industries.htm"},
{"id":"Sex discrimination","URI":"http://www.parliament.uk/topics/Sex-discrimination.htm"},
{"id":"Sexual offences","URI":"http://www.parliament.uk/topics/Sexual-offences.htm"},
{"id":"Shipping","URI":"http://www.parliament.uk/topics/Shipping.htm"},
{"id":"Sickness, disability and carers benefits","URI":"http://www.parliament.uk/topics/Sickness-disability-and-carers-benefits.htm"},
{"id":"Small businesses","URI":"http://www.parliament.uk/topics/Small-businesses.htm"},
{"id":"Small claims","URI":"http://www.parliament.uk/topics/Small-claims.htm"},
{"id":"Smoking","URI":"http://www.parliament.uk/topics/Smoking.htm"},
{"id":"Social rented housing","URI":"http://www.parliament.uk/topics/Social-rented-housing.htm"},
{"id":"Social Security and pensions","URI":"http://www.parliament.uk/topics/Social-Security-and-pensions.htm"},
{"id":"Social services","URI":"http://www.parliament.uk/topics/Social-services.htm"},
{"id":"Speaker","URI":"http://www.parliament.uk/topics/Speaker.htm"},
{"id":"Special educational needs","URI":"http://www.parliament.uk/topics/Special-educational-needs.htm"},
{"id":"Sports and Olympic Games","URI":"http://www.parliament.uk/topics/Sports-and-Olympic-Games.htm"},
{"id":"Standards","URI":"http://www.parliament.uk/topics/Standards.htm"},
{"id":"Statistics policy","URI":"http://www.parliament.uk/topics/Statistics-policy.htm"},
{"id":"Students","URI":"http://www.parliament.uk/topics/Students.htm"},
{"id":"Supported housing","URI":"http://www.parliament.uk/topics/Supported-housing.htm"},
{"id":"Sustainable development","URI":"http://www.parliament.uk/topics/Sustainable-development.htm"},
{"id":"Taxation","URI":"http://www.parliament.uk/topics/Taxation.htm"},
{"id":"Taxonomy","URI":"http://www.parliament.uk/topics/Taxonomy.htm"},
{"id":"Teachers","URI":"http://www.parliament.uk/topics/Teachers.htm"},
{"id":"Telecommunications","URI":"http://www.parliament.uk/topics/Telecommunications.htm"},
{"id":"Terrorism","URI":"http://www.parliament.uk/topics/Terrorism.htm"},
{"id":"Tourism","URI":"http://www.parliament.uk/topics/Tourism.htm"},
{"id":"Training","URI":"http://www.parliament.uk/topics/Training.htm"},
{"id":"Transport","URI":"http://www.parliament.uk/topics/Transport.htm"},
{"id":"Unemployment","URI":"http://www.parliament.uk/topics/Unemployment.htm"},
{"id":"United Nations","URI":"http://www.parliament.uk/topics/United-Nations.htm"},
{"id":"Utilities","URI":"http://www.parliament.uk/topics/Utilities.htm"},
{"id":"Vaccination","URI":"http://www.parliament.uk/topics/Vaccination.htm"},
{"id":"Veterans","URI":"http://www.parliament.uk/topics/Veterans.htm"},
{"id":"Voluntary organisations","URI":"http://www.parliament.uk/topics/Voluntary-organisations.htm"},
{"id":"Waste management","URI":"http://www.parliament.uk/topics/Waste-management.htm"},
{"id":"Water","URI":"http://www.parliament.uk/topics/Water.htm"},
{"id":"Water industry","URI":"http://www.parliament.uk/topics/Water-industry.htm"},
{"id":"Western Europe","URI":"http://www.parliament.uk/topics/Western-Europe.htm"},
{"id":"Western European Union","URI":"http://www.parliament.uk/topics/Western-European-Union.htm"},
{"id":"Wildlife","URI":"http://www.parliament.uk/topics/Wildlife.htm"},
{"id":"Wills and intestacy","URI":"http://www.parliament.uk/topics/Wills-and-intestacy.htm"},
{"id":"Working age benefits","URI":"http://www.parliament.uk/topics/Working-age-benefits.htm"},
{"id":"World economy","URI":"http://www.parliament.uk/topics/World-economy.htm"},
{"id":"Zimbabwe","URI":"http://www.parliament.uk/topics/Zimbabwe.htm"}
  ],
  "links": [
 {"color":"#333333", "source":0,"target":64},
{"color":"#b94431", "source":0,"target":62},
{"color":"#b94431", "source":0,"target":183},
{"color":"#333333", "source":1,"target":88},
{"color":"#333333", "source":1,"target":100},
{"color":"#333333", "source":2,"target":21},
{"color":"#333333", "source":2,"target":203},
{"color":"#333333", "source":3,"target":170},
{"color":"#b94431", "source":3,"target":313},
{"color":"#333333", "source":4,"target":107},
{"color":"#333333", "source":5,"target":7},
{"color":"#b94431", "source":5,"target":6},
{"color":"#b94431", "source":5,"target":51},
{"color":"#b94431", "source":5,"target":126},
{"color":"#b94431", "source":5,"target":223},
{"color":"#333333", "source":6,"target":5},
{"color":"#333333", "source":7,"target":291},
{"color":"#b94431", "source":7,"target":5},
{"color":"#b94431", "source":7,"target":14},
{"color":"#b94431", "source":7,"target":61},
{"color":"#b94431", "source":7,"target":131},
{"color":"#b94431", "source":7,"target":133},
{"color":"#b94431", "source":7,"target":135},
{"color":"#333333", "source":8,"target":144},
{"color":"#333333", "source":9,"target":64},
{"color":"#333333", "source":10,"target":98},
{"color":"#333333", "source":11,"target":14},
{"color":"#333333", "source":12,"target":198},
{"color":"#333333", "source":12,"target":267},
{"color":"#333333", "source":13,"target":14},
{"color":"#333333", "source":14,"target":7},
{"color":"#b94431", "source":14,"target":11},
{"color":"#b94431", "source":14,"target":13},
{"color":"#333333", "source":15,"target":64},
{"color":"#333333", "source":16,"target":73},
{"color":"#b94431", "source":16,"target":17},
{"color":"#b94431", "source":16,"target":302},
{"color":"#333333", "source":17,"target":16},
{"color":"#333333", "source":18,"target":76},
{"color":"#333333", "source":18,"target":170},
{"color":"#333333", "source":19,"target":20},
{"color":"#333333", "source":20,"target":69},
{"color":"#b94431", "source":20,"target":19},
{"color":"#b94431", "source":20,"target":207},
{"color":"#b94431", "source":20,"target":234},
{"color":"#333333", "source":21,"target":170},
{"color":"#b94431", "source":21,"target":2},
{"color":"#b94431", "source":21,"target":178},
{"color":"#333333", "source":22,"target":23},
{"color":"#333333", "source":23,"target":291},
{"color":"#b94431", "source":23,"target":22},
{"color":"#b94431", "source":23,"target":161},
{"color":"#b94431", "source":23,"target":211},
{"color":"#333333", "source":24,"target":170},
{"color":"#333333", "source":25,"target":297},
{"color":"#333333", "source":26,"target":76},
{"color":"#333333", "source":27,"target":280},
{"color":"#333333", "source":28,"target":280},
{"color":"#333333", "source":29,"target":280},
{"color":"#333333", "source":30,"target":106},
{"color":"#333333", "source":31,"target":166},
{"color":"#333333", "source":31,"target":196},
{"color":"#333333", "source":32,"target":72},
{"color":"#333333", "source":33,"target":264},
{"color":"#333333", "source":34,"target":35},
{"color":"#b94431", "source":34,"target":114},
{"color":"#b94431", "source":34,"target":256},
{"color":"#333333", "source":35,"target":291},
{"color":"#b94431", "source":35,"target":34},
{"color":"#b94431", "source":35,"target":55},
{"color":"#b94431", "source":35,"target":56},
{"color":"#b94431", "source":35,"target":59},
{"color":"#b94431", "source":35,"target":163},
{"color":"#b94431", "source":35,"target":164},
{"color":"#b94431", "source":35,"target":165},
{"color":"#b94431", "source":35,"target":167},
{"color":"#b94431", "source":35,"target":168},
{"color":"#b94431", "source":35,"target":176},
{"color":"#b94431", "source":35,"target":241},
{"color":"#b94431", "source":35,"target":259},
{"color":"#b94431", "source":35,"target":276},
{"color":"#b94431", "source":35,"target":285},
{"color":"#b94431", "source":35,"target":300},
{"color":"#333333", "source":36,"target":92},
{"color":"#333333", "source":37,"target":240},
{"color":"#333333", "source":38,"target":229},
{"color":"#b94431", "source":38,"target":47},
{"color":"#b94431", "source":38,"target":204},
{"color":"#b94431", "source":38,"target":214},
{"color":"#333333", "source":39,"target":53},
{"color":"#333333", "source":40,"target":42},
{"color":"#333333", "source":41,"target":42},
{"color":"#333333", "source":42,"target":53},
{"color":"#b94431", "source":42,"target":40},
{"color":"#b94431", "source":42,"target":41},
{"color":"#b94431", "source":42,"target":43},
{"color":"#b94431", "source":42,"target":80},
{"color":"#b94431", "source":42,"target":195},
{"color":"#b94431", "source":42,"target":258},
{"color":"#333333", "source":43,"target":42},
{"color":"#333333", "source":43,"target":281},
{"color":"#333333", "source":44,"target":229},
{"color":"#333333", "source":45,"target":64},
{"color":"#b94431", "source":45,"target":60},
{"color":"#b94431", "source":45,"target":141},
{"color":"#b94431", "source":45,"target":182},
{"color":"#b94431", "source":45,"target":188},
{"color":"#b94431", "source":45,"target":235},
{"color":"#b94431", "source":45,"target":242},
{"color":"#b94431", "source":45,"target":277},
{"color":"#333333", "source":46,"target":125},
{"color":"#333333", "source":47,"target":38},
{"color":"#333333", "source":48,"target":104},
{"color":"#333333", "source":48,"target":267},
{"color":"#333333", "source":49,"target":103},
{"color":"#333333", "source":50,"target":125},
{"color":"#333333", "source":51,"target":5},
{"color":"#333333", "source":51,"target":122},
{"color":"#333333", "source":52,"target":144},
{"color":"#333333", "source":53,"target":291},
{"color":"#b94431", "source":53,"target":39},
{"color":"#b94431", "source":53,"target":42},
{"color":"#b94431", "source":53,"target":72},
{"color":"#b94431", "source":53,"target":108},
{"color":"#b94431", "source":53,"target":125},
{"color":"#b94431", "source":53,"target":162},
{"color":"#b94431", "source":53,"target":222},
{"color":"#b94431", "source":53,"target":240},
{"color":"#b94431", "source":53,"target":260},
{"color":"#b94431", "source":53,"target":303},
{"color":"#333333", "source":54,"target":281},
{"color":"#333333", "source":55,"target":35},
{"color":"#333333", "source":56,"target":35},
{"color":"#333333", "source":57,"target":229},
{"color":"#333333", "source":58,"target":165},
{"color":"#333333", "source":59,"target":35},
{"color":"#333333", "source":60,"target":45},
{"color":"#333333", "source":60,"target":72},
{"color":"#333333", "source":61,"target":7},
{"color":"#333333", "source":61,"target":106},
{"color":"#333333", "source":62,"target":0},
{"color":"#333333", "source":63,"target":64},
{"color":"#b94431", "source":63,"target":65},
{"color":"#b94431", "source":63,"target":81},
{"color":"#b94431", "source":63,"target":177},
{"color":"#b94431", "source":63,"target":219},
{"color":"#b94431", "source":63,"target":251},
{"color":"#b94431", "source":63,"target":273},
{"color":"#333333", "source":64,"target":291},
{"color":"#b94431", "source":64,"target":0},
{"color":"#b94431", "source":64,"target":9},
{"color":"#b94431", "source":64,"target":15},
{"color":"#b94431", "source":64,"target":45},
{"color":"#b94431", "source":64,"target":63},
{"color":"#b94431", "source":64,"target":66},
{"color":"#b94431", "source":64,"target":72},
{"color":"#b94431", "source":64,"target":97},
{"color":"#b94431", "source":64,"target":98},
{"color":"#b94431", "source":64,"target":107},
{"color":"#b94431", "source":64,"target":125},
{"color":"#b94431", "source":64,"target":130},
{"color":"#b94431", "source":64,"target":136},
{"color":"#b94431", "source":64,"target":160},
{"color":"#b94431", "source":64,"target":169},
{"color":"#b94431", "source":64,"target":173},
{"color":"#b94431", "source":64,"target":180},
{"color":"#b94431", "source":64,"target":245},
{"color":"#b94431", "source":64,"target":246},
{"color":"#b94431", "source":64,"target":270},
{"color":"#b94431", "source":64,"target":294},
{"color":"#333333", "source":65,"target":63},
{"color":"#333333", "source":66,"target":64},
{"color":"#333333", "source":67,"target":229},
{"color":"#333333", "source":68,"target":69},
{"color":"#333333", "source":69,"target":291},
{"color":"#b94431", "source":69,"target":20},
{"color":"#b94431", "source":69,"target":68},
{"color":"#b94431", "source":69,"target":140},
{"color":"#b94431", "source":69,"target":185},
{"color":"#b94431", "source":69,"target":186},
{"color":"#b94431", "source":69,"target":187},
{"color":"#b94431", "source":69,"target":196},
{"color":"#b94431", "source":69,"target":210},
{"color":"#b94431", "source":69,"target":284},
{"color":"#b94431", "source":69,"target":295},
{"color":"#333333", "source":70,"target":264},
{"color":"#333333", "source":71,"target":246},
{"color":"#333333", "source":72,"target":53},
{"color":"#333333", "source":72,"target":64},
{"color":"#b94431", "source":72,"target":32},
{"color":"#b94431", "source":72,"target":60},
{"color":"#b94431", "source":72,"target":138},
{"color":"#b94431", "source":72,"target":310},
{"color":"#333333", "source":73,"target":291},
{"color":"#b94431", "source":73,"target":16},
{"color":"#b94431", "source":73,"target":74},
{"color":"#b94431", "source":73,"target":76},
{"color":"#b94431", "source":73,"target":203},
{"color":"#333333", "source":74,"target":73},
{"color":"#333333", "source":75,"target":76},
{"color":"#333333", "source":76,"target":73},
{"color":"#b94431", "source":76,"target":18},
{"color":"#b94431", "source":76,"target":26},
{"color":"#b94431", "source":76,"target":75},
{"color":"#b94431", "source":76,"target":111},
{"color":"#333333", "source":77,"target":229},
{"color":"#b94431", "source":77,"target":208},
{"color":"#b94431", "source":77,"target":216},
{"color":"#b94431", "source":77,"target":255},
{"color":"#b94431", "source":77,"target":269},
{"color":"#333333", "source":78,"target":107},
{"color":"#333333", "source":79,"target":147},
{"color":"#333333", "source":80,"target":42},
{"color":"#333333", "source":80,"target":125},
{"color":"#333333", "source":81,"target":63},
{"color":"#333333", "source":82,"target":144},
{"color":"#333333", "source":83,"target":118},
{"color":"#333333", "source":84,"target":122},
{"color":"#333333", "source":84,"target":172},
{"color":"#333333", "source":85,"target":87},
{"color":"#333333", "source":86,"target":87},
{"color":"#b94431", "source":86,"target":312},
{"color":"#333333", "source":87,"target":291},
{"color":"#b94431", "source":87,"target":85},
{"color":"#b94431", "source":87,"target":86},
{"color":"#b94431", "source":87,"target":109},
{"color":"#b94431", "source":87,"target":127},
{"color":"#b94431", "source":87,"target":128},
{"color":"#b94431", "source":87,"target":162},
{"color":"#b94431", "source":87,"target":171},
{"color":"#b94431", "source":87,"target":172},
{"color":"#b94431", "source":87,"target":176},
{"color":"#b94431", "source":87,"target":249},
{"color":"#b94431", "source":87,"target":257},
{"color":"#b94431", "source":87,"target":290},
{"color":"#333333", "source":88,"target":291},
{"color":"#b94431", "source":88,"target":1},
{"color":"#b94431", "source":88,"target":139},
{"color":"#b94431", "source":88,"target":150},
{"color":"#b94431", "source":88,"target":190},
{"color":"#b94431", "source":88,"target":220},
{"color":"#b94431", "source":88,"target":243},
{"color":"#b94431", "source":88,"target":266},
{"color":"#b94431", "source":88,"target":283},
{"color":"#b94431", "source":88,"target":287},
{"color":"#b94431", "source":88,"target":292},
{"color":"#333333", "source":89,"target":92},
{"color":"#333333", "source":90,"target":92},
{"color":"#333333", "source":90,"target":175},
{"color":"#333333", "source":91,"target":92},
{"color":"#333333", "source":92,"target":229},
{"color":"#b94431", "source":92,"target":36},
{"color":"#b94431", "source":92,"target":89},
{"color":"#b94431", "source":92,"target":90},
{"color":"#b94431", "source":92,"target":91},
{"color":"#b94431", "source":92,"target":93},
{"color":"#b94431", "source":92,"target":94},
{"color":"#b94431", "source":92,"target":95},
{"color":"#b94431", "source":92,"target":142},
{"color":"#333333", "source":93,"target":92},
{"color":"#333333", "source":94,"target":92},
{"color":"#333333", "source":95,"target":92},
{"color":"#333333", "source":96,"target":103},
{"color":"#333333", "source":97,"target":64},
{"color":"#333333", "source":98,"target":64},
{"color":"#b94431", "source":98,"target":10},
{"color":"#b94431", "source":98,"target":129},
{"color":"#b94431", "source":98,"target":237},
{"color":"#333333", "source":99,"target":100},
{"color":"#333333", "source":100,"target":291},
{"color":"#b94431", "source":100,"target":1},
{"color":"#b94431", "source":100,"target":99},
{"color":"#b94431", "source":100,"target":101},
{"color":"#b94431", "source":100,"target":209},
{"color":"#b94431", "source":100,"target":232},
{"color":"#b94431", "source":100,"target":233},
{"color":"#b94431", "source":100,"target":296},
{"color":"#b94431", "source":100,"target":298},
{"color":"#333333", "source":101,"target":100},
{"color":"#333333", "source":102,"target":154},
{"color":"#333333", "source":103,"target":104},
{"color":"#b94431", "source":103,"target":49},
{"color":"#b94431", "source":103,"target":96},
{"color":"#b94431", "source":103,"target":105},
{"color":"#b94431", "source":103,"target":137},
{"color":"#b94431", "source":103,"target":217},
{"color":"#b94431", "source":103,"target":221},
{"color":"#b94431", "source":103,"target":262},
{"color":"#333333", "source":104,"target":291},
{"color":"#b94431", "source":104,"target":48},
{"color":"#b94431", "source":104,"target":103},
{"color":"#b94431", "source":104,"target":106},
{"color":"#b94431", "source":104,"target":239},
{"color":"#b94431", "source":104,"target":300},
{"color":"#b94431", "source":104,"target":304},
{"color":"#b94431", "source":104,"target":305},
{"color":"#333333", "source":105,"target":103},
{"color":"#333333", "source":106,"target":104},
{"color":"#b94431", "source":106,"target":30},
{"color":"#b94431", "source":106,"target":61},
{"color":"#b94431", "source":106,"target":149},
{"color":"#b94431", "source":106,"target":194},
{"color":"#b94431", "source":106,"target":213},
{"color":"#b94431", "source":106,"target":309},
{"color":"#333333", "source":107,"target":64},
{"color":"#b94431", "source":107,"target":4},
{"color":"#b94431", "source":107,"target":78},
{"color":"#b94431", "source":107,"target":141},
{"color":"#b94431", "source":107,"target":252},
{"color":"#b94431", "source":107,"target":261},
{"color":"#b94431", "source":107,"target":272},
{"color":"#333333", "source":108,"target":53},
{"color":"#333333", "source":109,"target":87},
{"color":"#333333", "source":109,"target":122},
{"color":"#333333", "source":110,"target":115},
{"color":"#333333", "source":111,"target":76},
{"color":"#333333", "source":111,"target":122},
{"color":"#333333", "source":111,"target":170},
{"color":"#333333", "source":112,"target":122},
{"color":"#333333", "source":113,"target":122},
{"color":"#333333", "source":114,"target":34},
{"color":"#333333", "source":114,"target":122},
{"color":"#333333", "source":115,"target":122},
{"color":"#b94431", "source":115,"target":110},
{"color":"#b94431", "source":115,"target":119},
{"color":"#b94431", "source":115,"target":120},
{"color":"#b94431", "source":115,"target":121},
{"color":"#333333", "source":116,"target":122},
{"color":"#333333", "source":116,"target":173},
{"color":"#333333", "source":117,"target":122},
{"color":"#333333", "source":118,"target":170},
{"color":"#b94431", "source":118,"target":83},
{"color":"#b94431", "source":118,"target":265},
{"color":"#b94431", "source":118,"target":307},
{"color":"#333333", "source":119,"target":115},
{"color":"#333333", "source":120,"target":115},
{"color":"#333333", "source":121,"target":115},
{"color":"#333333", "source":122,"target":291},
{"color":"#b94431", "source":122,"target":51},
{"color":"#b94431", "source":122,"target":84},
{"color":"#b94431", "source":122,"target":109},
{"color":"#b94431", "source":122,"target":111},
{"color":"#b94431", "source":122,"target":112},
{"color":"#b94431", "source":122,"target":113},
{"color":"#b94431", "source":122,"target":114},
{"color":"#b94431", "source":122,"target":115},
{"color":"#b94431", "source":122,"target":116},
{"color":"#b94431", "source":122,"target":117},
{"color":"#333333", "source":123,"target":203},
{"color":"#333333", "source":123,"target":226},
{"color":"#333333", "source":124,"target":280},
{"color":"#333333", "source":125,"target":53},
{"color":"#333333", "source":125,"target":64},
{"color":"#b94431", "source":125,"target":46},
{"color":"#b94431", "source":125,"target":50},
{"color":"#b94431", "source":125,"target":80},
{"color":"#b94431", "source":125,"target":195},
{"color":"#333333", "source":126,"target":5},
{"color":"#333333", "source":127,"target":87},
{"color":"#333333", "source":128,"target":87},
{"color":"#b94431", "source":128,"target":167},
{"color":"#b94431", "source":128,"target":189},
{"color":"#b94431", "source":128,"target":205},
{"color":"#b94431", "source":128,"target":233},
{"color":"#333333", "source":129,"target":98},
{"color":"#333333", "source":130,"target":64},
{"color":"#333333", "source":131,"target":7},
{"color":"#333333", "source":132,"target":305},
{"color":"#333333", "source":133,"target":7},
{"color":"#333333", "source":134,"target":170},
{"color":"#333333", "source":135,"target":7},
{"color":"#333333", "source":136,"target":64},
{"color":"#333333", "source":136,"target":229},
{"color":"#333333", "source":137,"target":103},
{"color":"#333333", "source":137,"target":162},
{"color":"#333333", "source":138,"target":72},
{"color":"#333333", "source":139,"target":88},
{"color":"#333333", "source":140,"target":69},
{"color":"#333333", "source":141,"target":45},
{"color":"#333333", "source":141,"target":107},
{"color":"#333333", "source":142,"target":92},
{"color":"#333333", "source":143,"target":198},
{"color":"#333333", "source":143,"target":267},
{"color":"#333333", "source":144,"target":147},
{"color":"#b94431", "source":144,"target":8},
{"color":"#b94431", "source":144,"target":52},
{"color":"#b94431", "source":144,"target":82},
{"color":"#b94431", "source":144,"target":218},
{"color":"#b94431", "source":144,"target":278},
{"color":"#b94431", "source":144,"target":301},
{"color":"#333333", "source":145,"target":147},
{"color":"#333333", "source":146,"target":147},
{"color":"#b94431", "source":146,"target":201},
{"color":"#333333", "source":147,"target":291},
{"color":"#b94431", "source":147,"target":79},
{"color":"#b94431", "source":147,"target":144},
{"color":"#b94431", "source":147,"target":145},
{"color":"#b94431", "source":147,"target":146},
{"color":"#b94431", "source":147,"target":148},
{"color":"#b94431", "source":147,"target":197},
{"color":"#b94431", "source":147,"target":198},
{"color":"#b94431", "source":147,"target":231},
{"color":"#333333", "source":148,"target":147},
{"color":"#333333", "source":149,"target":106},
{"color":"#333333", "source":150,"target":88},
{"color":"#333333", "source":151,"target":154},
{"color":"#333333", "source":152,"target":228},
{"color":"#333333", "source":153,"target":228},
{"color":"#333333", "source":154,"target":156},
{"color":"#b94431", "source":154,"target":102},
{"color":"#b94431", "source":154,"target":151},
{"color":"#b94431", "source":154,"target":155},
{"color":"#b94431", "source":154,"target":158},
{"color":"#b94431", "source":154,"target":159},
{"color":"#b94431", "source":154,"target":225},
{"color":"#b94431", "source":154,"target":227},
{"color":"#b94431", "source":154,"target":247},
{"color":"#b94431", "source":154,"target":279},
{"color":"#b94431", "source":154,"target":288},
{"color":"#333333", "source":155,"target":154},
{"color":"#333333", "source":156,"target":291},
{"color":"#b94431", "source":156,"target":154},
{"color":"#b94431", "source":156,"target":157},
{"color":"#b94431", "source":156,"target":236},
{"color":"#333333", "source":157,"target":156},
{"color":"#333333", "source":157,"target":280},
{"color":"#333333", "source":158,"target":154},
{"color":"#333333", "source":159,"target":154},
{"color":"#333333", "source":160,"target":64},
{"color":"#333333", "source":160,"target":170},
{"color":"#333333", "source":161,"target":23},
{"color":"#333333", "source":162,"target":53},
{"color":"#333333", "source":162,"target":87},
{"color":"#b94431", "source":162,"target":137},
{"color":"#333333", "source":163,"target":35},
{"color":"#333333", "source":164,"target":35},
{"color":"#333333", "source":165,"target":35},
{"color":"#b94431", "source":165,"target":58},
{"color":"#b94431", "source":165,"target":193},
{"color":"#b94431", "source":165,"target":271},
{"color":"#b94431", "source":165,"target":295},
{"color":"#333333", "source":166,"target":268},
{"color":"#b94431", "source":166,"target":31},
{"color":"#b94431", "source":166,"target":177},
{"color":"#b94431", "source":166,"target":293},
{"color":"#333333", "source":167,"target":35},
{"color":"#333333", "source":167,"target":128},
{"color":"#333333", "source":168,"target":35},
{"color":"#333333", "source":169,"target":64},
{"color":"#333333", "source":170,"target":291},
{"color":"#b94431", "source":170,"target":3},
{"color":"#b94431", "source":170,"target":18},
{"color":"#b94431", "source":170,"target":21},
{"color":"#b94431", "source":170,"target":24},
{"color":"#b94431", "source":170,"target":111},
{"color":"#b94431", "source":170,"target":118},
{"color":"#b94431", "source":170,"target":134},
{"color":"#b94431", "source":170,"target":160},
{"color":"#b94431", "source":170,"target":171},
{"color":"#b94431", "source":170,"target":172},
{"color":"#b94431", "source":170,"target":173},
{"color":"#b94431", "source":170,"target":174},
{"color":"#b94431", "source":170,"target":175},
{"color":"#b94431", "source":170,"target":181},
{"color":"#b94431", "source":170,"target":202},
{"color":"#b94431", "source":170,"target":215},
{"color":"#b94431", "source":170,"target":226},
{"color":"#b94431", "source":170,"target":294},
{"color":"#333333", "source":171,"target":87},
{"color":"#333333", "source":171,"target":170},
{"color":"#333333", "source":172,"target":87},
{"color":"#333333", "source":172,"target":170},
{"color":"#b94431", "source":172,"target":84},
{"color":"#333333", "source":173,"target":64},
{"color":"#333333", "source":173,"target":170},
{"color":"#b94431", "source":173,"target":116},
{"color":"#333333", "source":174,"target":170},
{"color":"#b94431", "source":174,"target":212},
{"color":"#b94431", "source":174,"target":224},
{"color":"#b94431", "source":174,"target":299},
{"color":"#b94431", "source":174,"target":308},
{"color":"#333333", "source":175,"target":170},
{"color":"#b94431", "source":175,"target":90},
{"color":"#333333", "source":176,"target":35},
{"color":"#333333", "source":176,"target":87},
{"color":"#333333", "source":177,"target":63},
{"color":"#333333", "source":177,"target":166},
{"color":"#333333", "source":178,"target":21},
{"color":"#333333", "source":178,"target":202},
{"color":"#333333", "source":179,"target":202},
{"color":"#333333", "source":179,"target":203},
{"color":"#333333", "source":180,"target":64},
{"color":"#333333", "source":181,"target":170},
{"color":"#333333", "source":182,"target":45},
{"color":"#333333", "source":183,"target":0},
{"color":"#333333", "source":184,"target":229},
{"color":"#333333", "source":185,"target":69},
{"color":"#333333", "source":186,"target":69},
{"color":"#333333", "source":187,"target":69},
{"color":"#333333", "source":188,"target":45},
{"color":"#333333", "source":189,"target":128},
{"color":"#333333", "source":190,"target":88},
{"color":"#333333", "source":191,"target":229},
{"color":"#333333", "source":192,"target":228},
{"color":"#333333", "source":193,"target":165},
{"color":"#333333", "source":194,"target":106},
{"color":"#333333", "source":195,"target":42},
{"color":"#333333", "source":195,"target":125},
{"color":"#333333", "source":196,"target":69},
{"color":"#b94431", "source":196,"target":31},
{"color":"#b94431", "source":196,"target":244},
{"color":"#333333", "source":197,"target":147},
{"color":"#333333", "source":198,"target":147},
{"color":"#b94431", "source":198,"target":12},
{"color":"#b94431", "source":198,"target":143},
{"color":"#333333", "source":199,"target":228},
{"color":"#333333", "source":200,"target":228},
{"color":"#333333", "source":201,"target":146},
{"color":"#333333", "source":202,"target":170},
{"color":"#b94431", "source":202,"target":178},
{"color":"#b94431", "source":202,"target":179},
{"color":"#333333", "source":203,"target":73},
{"color":"#b94431", "source":203,"target":2},
{"color":"#b94431", "source":203,"target":123},
{"color":"#b94431", "source":203,"target":179},
{"color":"#333333", "source":204,"target":38},
{"color":"#333333", "source":205,"target":128},
{"color":"#333333", "source":206,"target":264},
{"color":"#333333", "source":207,"target":20},
{"color":"#333333", "source":208,"target":77},
{"color":"#333333", "source":209,"target":100},
{"color":"#333333", "source":209,"target":290},
{"color":"#333333", "source":210,"target":69},
{"color":"#333333", "source":211,"target":23},
{"color":"#333333", "source":212,"target":174},
{"color":"#333333", "source":213,"target":106},
{"color":"#333333", "source":214,"target":38},
{"color":"#333333", "source":215,"target":170},
{"color":"#333333", "source":216,"target":77},
{"color":"#333333", "source":217,"target":103},
{"color":"#333333", "source":218,"target":144},
{"color":"#333333", "source":219,"target":63},
{"color":"#333333", "source":220,"target":88},
{"color":"#333333", "source":221,"target":103},
{"color":"#333333", "source":222,"target":53},
{"color":"#333333", "source":223,"target":5},
{"color":"#333333", "source":224,"target":174},
{"color":"#333333", "source":225,"target":154},
{"color":"#333333", "source":226,"target":170},
{"color":"#b94431", "source":226,"target":123},
{"color":"#333333", "source":227,"target":154},
{"color":"#333333", "source":228,"target":229},
{"color":"#b94431", "source":228,"target":152},
{"color":"#b94431", "source":228,"target":153},
{"color":"#b94431", "source":228,"target":192},
{"color":"#b94431", "source":228,"target":199},
{"color":"#b94431", "source":228,"target":200},
{"color":"#b94431", "source":228,"target":230},
{"color":"#b94431", "source":228,"target":282},
{"color":"#333333", "source":229,"target":291},
{"color":"#b94431", "source":229,"target":38},
{"color":"#b94431", "source":229,"target":44},
{"color":"#b94431", "source":229,"target":57},
{"color":"#b94431", "source":229,"target":67},
{"color":"#b94431", "source":229,"target":77},
{"color":"#b94431", "source":229,"target":92},
{"color":"#b94431", "source":229,"target":136},
{"color":"#b94431", "source":229,"target":184},
{"color":"#b94431", "source":229,"target":191},
{"color":"#b94431", "source":229,"target":228},
{"color":"#b94431", "source":229,"target":238},
{"color":"#b94431", "source":229,"target":248},
{"color":"#b94431", "source":229,"target":250},
{"color":"#b94431", "source":229,"target":286},
{"color":"#333333", "source":230,"target":228},
{"color":"#333333", "source":231,"target":147},
{"color":"#333333", "source":232,"target":100},
{"color":"#333333", "source":233,"target":100},
{"color":"#333333", "source":233,"target":128},
{"color":"#333333", "source":233,"target":280},
{"color":"#333333", "source":234,"target":20},
{"color":"#333333", "source":235,"target":45},
{"color":"#333333", "source":236,"target":156},
{"color":"#b94431", "source":236,"target":254},
{"color":"#b94431", "source":236,"target":257},
{"color":"#b94431", "source":236,"target":289},
{"color":"#333333", "source":237,"target":98},
{"color":"#333333", "source":238,"target":229},
{"color":"#333333", "source":239,"target":104},
{"color":"#333333", "source":240,"target":53},
{"color":"#b94431", "source":240,"target":37},
{"color":"#333333", "source":241,"target":35},
{"color":"#333333", "source":242,"target":45},
{"color":"#333333", "source":243,"target":88},
{"color":"#333333", "source":244,"target":196},
{"color":"#333333", "source":245,"target":64},
{"color":"#333333", "source":246,"target":64},
{"color":"#b94431", "source":246,"target":71},
{"color":"#333333", "source":247,"target":154},
{"color":"#333333", "source":248,"target":229},
{"color":"#333333", "source":249,"target":87},
{"color":"#333333", "source":250,"target":229},
{"color":"#333333", "source":251,"target":63},
{"color":"#333333", "source":252,"target":107},
{"color":"#333333", "source":253,"target":297},
{"color":"#333333", "source":254,"target":236},
{"color":"#333333", "source":255,"target":77},
{"color":"#333333", "source":256,"target":34},
{"color":"#333333", "source":257,"target":87},
{"color":"#333333", "source":257,"target":236},
{"color":"#333333", "source":258,"target":42},
{"color":"#333333", "source":259,"target":35},
{"color":"#333333", "source":260,"target":53},
{"color":"#333333", "source":261,"target":107},
{"color":"#333333", "source":262,"target":103},
{"color":"#333333", "source":263,"target":268},
{"color":"#333333", "source":264,"target":297},
{"color":"#b94431", "source":264,"target":33},
{"color":"#b94431", "source":264,"target":70},
{"color":"#b94431", "source":264,"target":206},
{"color":"#333333", "source":265,"target":118},
{"color":"#333333", "source":266,"target":88},
{"color":"#333333", "source":267,"target":268},
{"color":"#b94431", "source":267,"target":12},
{"color":"#b94431", "source":267,"target":48},
{"color":"#b94431", "source":267,"target":143},
{"color":"#333333", "source":268,"target":291},
{"color":"#b94431", "source":268,"target":166},
{"color":"#b94431", "source":268,"target":263},
{"color":"#b94431", "source":268,"target":267},
{"color":"#333333", "source":269,"target":77},
{"color":"#333333", "source":270,"target":64},
{"color":"#333333", "source":271,"target":165},
{"color":"#333333", "source":272,"target":107},
{"color":"#333333", "source":273,"target":63},
{"color":"#333333", "source":274,"target":297},
{"color":"#333333", "source":275,"target":280},
{"color":"#333333", "source":276,"target":35},
{"color":"#333333", "source":277,"target":45},
{"color":"#333333", "source":278,"target":144},
{"color":"#333333", "source":279,"target":154},
{"color":"#333333", "source":280,"target":291},
{"color":"#b94431", "source":280,"target":27},
{"color":"#b94431", "source":280,"target":28},
{"color":"#b94431", "source":280,"target":29},
{"color":"#b94431", "source":280,"target":124},
{"color":"#b94431", "source":280,"target":157},
{"color":"#b94431", "source":280,"target":233},
{"color":"#b94431", "source":280,"target":275},
{"color":"#b94431", "source":280,"target":311},
{"color":"#333333", "source":281,"target":291},
{"color":"#b94431", "source":281,"target":43},
{"color":"#b94431", "source":281,"target":54},
{"color":"#333333", "source":282,"target":228},
{"color":"#333333", "source":283,"target":88},
{"color":"#333333", "source":284,"target":69},
{"color":"#333333", "source":285,"target":35},
{"color":"#333333", "source":286,"target":229},
{"color":"#333333", "source":287,"target":88},
{"color":"#333333", "source":288,"target":154},
{"color":"#333333", "source":289,"target":236},
{"color":"#333333", "source":290,"target":87},
{"color":"#b94431", "source":290,"target":209},
{"color":"#b94431", "source":291,"target":7},
{"color":"#b94431", "source":291,"target":23},
{"color":"#b94431", "source":291,"target":35},
{"color":"#b94431", "source":291,"target":53},
{"color":"#b94431", "source":291,"target":64},
{"color":"#b94431", "source":291,"target":69},
{"color":"#b94431", "source":291,"target":73},
{"color":"#b94431", "source":291,"target":87},
{"color":"#b94431", "source":291,"target":88},
{"color":"#b94431", "source":291,"target":100},
{"color":"#b94431", "source":291,"target":104},
{"color":"#b94431", "source":291,"target":122},
{"color":"#b94431", "source":291,"target":147},
{"color":"#b94431", "source":291,"target":156},
{"color":"#b94431", "source":291,"target":170},
{"color":"#b94431", "source":291,"target":229},
{"color":"#b94431", "source":291,"target":268},
{"color":"#b94431", "source":291,"target":280},
{"color":"#b94431", "source":291,"target":281},
{"color":"#b94431", "source":291,"target":297},
{"color":"#333333", "source":292,"target":88},
{"color":"#333333", "source":293,"target":166},
{"color":"#333333", "source":294,"target":64},
{"color":"#333333", "source":294,"target":170},
{"color":"#333333", "source":295,"target":69},
{"color":"#333333", "source":295,"target":165},
{"color":"#333333", "source":296,"target":100},
{"color":"#333333", "source":297,"target":291},
{"color":"#b94431", "source":297,"target":25},
{"color":"#b94431", "source":297,"target":253},
{"color":"#b94431", "source":297,"target":264},
{"color":"#b94431", "source":297,"target":274},
{"color":"#333333", "source":298,"target":100},
{"color":"#333333", "source":299,"target":174},
{"color":"#333333", "source":300,"target":35},
{"color":"#333333", "source":300,"target":104},
{"color":"#333333", "source":301,"target":144},
{"color":"#333333", "source":302,"target":16},
{"color":"#333333", "source":303,"target":53},
{"color":"#333333", "source":304,"target":104},
{"color":"#333333", "source":305,"target":104},
{"color":"#b94431", "source":305,"target":132},
{"color":"#b94431", "source":305,"target":306},
{"color":"#333333", "source":306,"target":305},
{"color":"#333333", "source":307,"target":118},
{"color":"#333333", "source":308,"target":174},
{"color":"#333333", "source":309,"target":106},
{"color":"#333333", "source":310,"target":72},
{"color":"#333333", "source":311,"target":280},
{"color":"#333333", "source":312,"target":86},
{"color":"#333333", "source":313,"target":3}
  ],
  "multigraph": false
}